gyankosh/__init__.py
gyankosh-0.0.1.dist-info/LICENSE
gyankosh-0.0.1.dist-info/METADATA
gyankosh-0.0.1.dist-info/WHEEL
gyankosh-0.0.1.dist-info/RECORD
