Metadata-Version: 2.1
Name: gyankosh
Version: 0.0.1
Summary: Unified, security-first, user-local knowledgebase with built-in RAG and Vector Store
License: MIT
Author: Tridib Roy Arjo
Requires-Python: >=3.10,<4.0
Classifier: License :: OSI Approved :: MIT License
Classifier: Programming Language :: Python :: 3
Classifier: Programming Language :: Python :: 3.10
Classifier: Programming Language :: Python :: 3.11
Classifier: Programming Language :: Python :: 3.12
